[
 {
  "조회기간 : 2022.01 ~ 2022.12, 여객 : 전체, 화물 : 전체, 운항 : 전체, 노선 : 전체, 공항 : 인천(ICN), 상대공항 : 전체, 출발\/도착 : 출발": "노선",
  "Column2": "노선",
  "Column3": "운항(편)",
  "Column4": "여객(명)",
  "Column5": "화물(톤)"
 },
 {
  "조회기간 : 2022.01 ~ 2022.12, 여객 : 전체, 화물 : 전체, 운항 : 전체, 노선 : 전체, 공항 : 인천(ICN), 상대공항 : 전체, 출발\/도착 : 출발": "전체 합계",
  "Column3": 85917,
  "Column4": 8929505,
  "Column5": 1645649
 },
 {
  "조회기간 : 2022.01 ~ 2022.12, 여객 : 전체, 화물 : 전체, 운항 : 전체, 노선 : 전체, 공항 : 인천(ICN), 상대공항 : 전체, 출발\/도착 : 출발": "인천(ICN)",
  "Column2": "방콕(BKK)",
  "Column3": 3221,
  "Column4": 633969,
  "Column5": 34362
 },
 {
  "조회기간 : 2022.01 ~ 2022.12, 여객 : 전체, 화물 : 전체, 운항 : 전체, 노선 : 전체, 공항 : 인천(ICN), 상대공항 : 전체, 출발\/도착 : 출발": "인천(ICN)",
  "Column2": "싱가폴(SIN)",
  "Column3": 2533,
  "Column4": 498868,
  "Column5": 53599
 },
 {
  "조회기간 : 2022.01 ~ 2022.12, 여객 : 전체, 화물 : 전체, 운항 : 전체, 노선 : 전체, 공항 : 인천(ICN), 상대공항 : 전체, 출발\/도착 : 출발": "인천(ICN)",
  "Column2": "호치민(SGN)",
  "Column3": 2763,
  "Column4": 449911,
  "Column5": 31378
 },
 {
  "조회기간 : 2022.01 ~ 2022.12, 여객 : 전체, 화물 : 전체, 운항 : 전체, 노선 : 전체, 공항 : 인천(ICN), 상대공항 : 전체, 출발\/도착 : 출발": "인천(ICN)",
  "Column2": "나리타(NRT)",
  "Column3": 4085,
  "Column4": 431352,
  "Column5": 74023
 },
 {
  "조회기간 : 2022.01 ~ 2022.12, 여객 : 전체, 화물 : 전체, 운항 : 전체, 노선 : 전체, 공항 : 인천(ICN), 상대공항 : 전체, 출발\/도착 : 출발": "인천(ICN)",
  "Column2": "마닐라(MNL)",
  "Column3": 2180,
  "Column4": 394348,
  "Column5": 25944
 },
 {
  "조회기간 : 2022.01 ~ 2022.12, 여객 : 전체, 화물 : 전체, 운항 : 전체, 노선 : 전체, 공항 : 인천(ICN), 상대공항 : 전체, 출발\/도착 : 출발": "인천(ICN)",
  "Column2": "간사이(KIX)",
  "Column3": 2815,
  "Column4": 344518,
  "Column5": 34239
 },
 {
  "조회기간 : 2022.01 ~ 2022.12, 여객 : 전체, 화물 : 전체, 운항 : 전체, 노선 : 전체, 공항 : 인천(ICN), 상대공항 : 전체, 출발\/도착 : 출발": "인천(ICN)",
  "Column2": "하노이(HAN)",
  "Column3": 3533,
  "Column4": 338792,
  "Column5": 98261
 },
 {
  "조회기간 : 2022.01 ~ 2022.12, 여객 : 전체, 화물 : 전체, 운항 : 전체, 노선 : 전체, 공항 : 인천(ICN), 상대공항 : 전체, 출발\/도착 : 출발": "인천(ICN)",
  "Column2": "로스앤젤레스(LAX)",
  "Column3": 4123,
  "Column4": 327625,
  "Column5": 134166
 },
 {
  "조회기간 : 2022.01 ~ 2022.12, 여객 : 전체, 화물 : 전체, 운항 : 전체, 노선 : 전체, 공항 : 인천(ICN), 상대공항 : 전체, 출발\/도착 : 출발": "인천(ICN)",
  "Column2": "다낭(DAD)",
  "Column3": 1731,
  "Column4": 281344,
  "Column5": 3095
 },
 {
  "조회기간 : 2022.01 ~ 2022.12, 여객 : 전체, 화물 : 전체, 운항 : 전체, 노선 : 전체, 공항 : 인천(ICN), 상대공항 : 전체, 출발\/도착 : 출발": "인천(ICN)",
  "Column2": "후쿠오카(FUK)",
  "Column3": 1377,
  "Column4": 219330,
  "Column5": 2073
 },
 {
  "조회기간 : 2022.01 ~ 2022.12, 여객 : 전체, 화물 : 전체, 운항 : 전체, 노선 : 전체, 공항 : 인천(ICN), 상대공항 : 전체, 출발\/도착 : 출발": "인천(ICN)",
  "Column2": "뉴욕(JFK)",
  "Column3": 1557,
  "Column4": 215688,
  "Column5": 43857
 },
 {
  "조회기간 : 2022.01 ~ 2022.12, 여객 : 전체, 화물 : 전체, 운항 : 전체, 노선 : 전체, 공항 : 인천(ICN), 상대공항 : 전체, 출발\/도착 : 출발": "인천(ICN)",
  "Column2": "샌프란시스코(SFO)",
  "Column3": 1344,
  "Column4": 201739,
  "Column5": 22477
 },
 {
  "조회기간 : 2022.01 ~ 2022.12, 여객 : 전체, 화물 : 전체, 운항 : 전체, 노선 : 전체, 공항 : 인천(ICN), 상대공항 : 전체, 출발\/도착 : 출발": "인천(ICN)",
  "Column2": "괌(GUM)",
  "Column3": 1201,
  "Column4": 191609,
  "Column5": 4553
 },
 {
  "조회기간 : 2022.01 ~ 2022.12, 여객 : 전체, 화물 : 전체, 운항 : 전체, 노선 : 전체, 공항 : 인천(ICN), 상대공항 : 전체, 출발\/도착 : 출발": "인천(ICN)",
  "Column2": "파리(CDG)",
  "Column3": 635,
  "Column4": 158033,
  "Column5": 10565
 },
 {
  "조회기간 : 2022.01 ~ 2022.12, 여객 : 전체, 화물 : 전체, 운항 : 전체, 노선 : 전체, 공항 : 인천(ICN), 상대공항 : 전체, 출발\/도착 : 출발": "인천(ICN)",
  "Column2": "아틀란타(ATL)",
  "Column3": 1145,
  "Column4": 156797,
  "Column5": 38220
 },
 {
  "조회기간 : 2022.01 ~ 2022.12, 여객 : 전체, 화물 : 전체, 운항 : 전체, 노선 : 전체, 공항 : 인천(ICN), 상대공항 : 전체, 출발\/도착 : 출발": "인천(ICN)",
  "Column2": "프랑크푸르트(FRA)",
  "Column3": 2299,
  "Column4": 149186,
  "Column5": 68428
 },
 {
  "조회기간 : 2022.01 ~ 2022.12, 여객 : 전체, 화물 : 전체, 운항 : 전체, 노선 : 전체, 공항 : 인천(ICN), 상대공항 : 전체, 출발\/도착 : 출발": "인천(ICN)",
  "Column2": "호놀룰루(HNL)",
  "Column3": 699,
  "Column4": 147513,
  "Column5": 9580
 },
 {
  "조회기간 : 2022.01 ~ 2022.12, 여객 : 전체, 화물 : 전체, 운항 : 전체, 노선 : 전체, 공항 : 인천(ICN), 상대공항 : 전체, 출발\/도착 : 출발": "인천(ICN)",
  "Column2": "두바이(DXB)",
  "Column3": 412,
  "Column4": 144203,
  "Column5": 8784
 },
 {
  "조회기간 : 2022.01 ~ 2022.12, 여객 : 전체, 화물 : 전체, 운항 : 전체, 노선 : 전체, 공항 : 인천(ICN), 상대공항 : 전체, 출발\/도착 : 출발": "인천(ICN)",
  "Column2": "시애틀(SEA)",
  "Column3": 1106,
  "Column4": 139367,
  "Column5": 10165
 },
 {
  "조회기간 : 2022.01 ~ 2022.12, 여객 : 전체, 화물 : 전체, 운항 : 전체, 노선 : 전체, 공항 : 인천(ICN), 상대공항 : 전체, 출발\/도착 : 출발": "인천(ICN)",
  "Column2": "이스탄불(IST)",
  "Column3": 585,
  "Column4": 136601,
  "Column5": 16022
 },
 {
  "조회기간 : 2022.01 ~ 2022.12, 여객 : 전체, 화물 : 전체, 운항 : 전체, 노선 : 전체, 공항 : 인천(ICN), 상대공항 : 전체, 출발\/도착 : 출발": "인천(ICN)",
  "Column2": "울란바토르 신공항(UBN)",
  "Column3": 981,
  "Column4": 136109,
  "Column5": 8717
 },
 {
  "조회기간 : 2022.01 ~ 2022.12, 여객 : 전체, 화물 : 전체, 운항 : 전체, 노선 : 전체, 공항 : 인천(ICN), 상대공항 : 전체, 출발\/도착 : 출발": "인천(ICN)",
  "Column2": "뱅쿠버(YVR)",
  "Column3": 569,
  "Column4": 135020,
  "Column5": 9777
 },
 {
  "조회기간 : 2022.01 ~ 2022.12, 여객 : 전체, 화물 : 전체, 운항 : 전체, 노선 : 전체, 공항 : 인천(ICN), 상대공항 : 전체, 출발\/도착 : 출발": "인천(ICN)",
  "Column2": "대북(TPE)",
  "Column3": 2870,
  "Column4": 123560,
  "Column5": 50320
 },
 {
  "조회기간 : 2022.01 ~ 2022.12, 여객 : 전체, 화물 : 전체, 운항 : 전체, 노선 : 전체, 공항 : 인천(ICN), 상대공항 : 전체, 출발\/도착 : 출발": "인천(ICN)",
  "Column2": "세부(CEB)",
  "Column3": 796,
  "Column4": 116978,
  "Column5": 2537
 },
 {
  "조회기간 : 2022.01 ~ 2022.12, 여객 : 전체, 화물 : 전체, 운항 : 전체, 노선 : 전체, 공항 : 인천(ICN), 상대공항 : 전체, 출발\/도착 : 출발": "인천(ICN)",
  "Column2": "도하(DOH)",
  "Column3": 574,
  "Column4": 115146,
  "Column5": 27093
 },
 {
  "조회기간 : 2022.01 ~ 2022.12, 여객 : 전체, 화물 : 전체, 운항 : 전체, 노선 : 전체, 공항 : 인천(ICN), 상대공항 : 전체, 출발\/도착 : 출발": "인천(ICN)",
  "Column2": "자카르타(CGK)",
  "Column3": 711,
  "Column4": 114841,
  "Column5": 15752
 },
 {
  "조회기간 : 2022.01 ~ 2022.12, 여객 : 전체, 화물 : 전체, 운항 : 전체, 노선 : 전체, 공항 : 인천(ICN), 상대공항 : 전체, 출발\/도착 : 출발": "인천(ICN)",
  "Column2": "쿠알라룸푸르(KUL)",
  "Column3": 955,
  "Column4": 112372,
  "Column5": 18414
 },
 {
  "조회기간 : 2022.01 ~ 2022.12, 여객 : 전체, 화물 : 전체, 운항 : 전체, 노선 : 전체, 공항 : 인천(ICN), 상대공항 : 전체, 출발\/도착 : 출발": "인천(ICN)",
  "Column2": "나트랑캄란(CXR)",
  "Column3": 654,
  "Column4": 111196,
  "Column5": 1022
 },
 {
  "조회기간 : 2022.01 ~ 2022.12, 여객 : 전체, 화물 : 전체, 운항 : 전체, 노선 : 전체, 공항 : 인천(ICN), 상대공항 : 전체, 출발\/도착 : 출발": "인천(ICN)",
  "Column2": "홍콩(HKG)",
  "Column3": 3024,
  "Column4": 110603,
  "Column5": 108819
 },
 {
  "조회기간 : 2022.01 ~ 2022.12, 여객 : 전체, 화물 : 전체, 운항 : 전체, 노선 : 전체, 공항 : 인천(ICN), 상대공항 : 전체, 출발\/도착 : 출발": "인천(ICN)",
  "Column2": "달라스(DFW)",
  "Column3": 868,
  "Column4": 108638,
  "Column5": 36001
 },
 {
  "조회기간 : 2022.01 ~ 2022.12, 여객 : 전체, 화물 : 전체, 운항 : 전체, 노선 : 전체, 공항 : 인천(ICN), 상대공항 : 전체, 출발\/도착 : 출발": "인천(ICN)",
  "Column2": "토론토(YYZ)",
  "Column3": 827,
  "Column4": 106267,
  "Column5": 14922
 },
 {
  "조회기간 : 2022.01 ~ 2022.12, 여객 : 전체, 화물 : 전체, 운항 : 전체, 노선 : 전체, 공항 : 인천(ICN), 상대공항 : 전체, 출발\/도착 : 출발": "인천(ICN)",
  "Column2": "프롬펜(PNH)",
  "Column3": 678,
  "Column4": 105367,
  "Column5": 3762
 },
 {
  "조회기간 : 2022.01 ~ 2022.12, 여객 : 전체, 화물 : 전체, 운항 : 전체, 노선 : 전체, 공항 : 인천(ICN), 상대공항 : 전체, 출발\/도착 : 출발": "인천(ICN)",
  "Column2": "시드니(SYD)",
  "Column3": 588,
  "Column4": 101685,
  "Column5": 3802
 },
 {
  "조회기간 : 2022.01 ~ 2022.12, 여객 : 전체, 화물 : 전체, 운항 : 전체, 노선 : 전체, 공항 : 인천(ICN), 상대공항 : 전체, 출발\/도착 : 출발": "인천(ICN)",
  "Column2": "아부다비(AUH)",
  "Column3": 365,
  "Column4": 86316,
  "Column5": 7012
 },
 {
  "조회기간 : 2022.01 ~ 2022.12, 여객 : 전체, 화물 : 전체, 운항 : 전체, 노선 : 전체, 공항 : 인천(ICN), 상대공항 : 전체, 출발\/도착 : 출발": "인천(ICN)",
  "Column2": "클라크 필드(CRK)",
  "Column3": 542,
  "Column4": 82634,
  "Column5": 3131
 },
 {
  "조회기간 : 2022.01 ~ 2022.12, 여객 : 전체, 화물 : 전체, 운항 : 전체, 노선 : 전체, 공항 : 인천(ICN), 상대공항 : 전체, 출발\/도착 : 출발": "인천(ICN)",
  "Column2": "런던히드로(LHR)",
  "Column3": 545,
  "Column4": 78408,
  "Column5": 15444
 },
 {
  "조회기간 : 2022.01 ~ 2022.12, 여객 : 전체, 화물 : 전체, 운항 : 전체, 노선 : 전체, 공항 : 인천(ICN), 상대공항 : 전체, 출발\/도착 : 출발": "인천(ICN)",
  "Column2": "사이판(SPN)",
  "Column3": 500,
  "Column4": 70090,
  "Column5": 1034
 },
 {
  "조회기간 : 2022.01 ~ 2022.12, 여객 : 전체, 화물 : 전체, 운항 : 전체, 노선 : 전체, 공항 : 인천(ICN), 상대공항 : 전체, 출발\/도착 : 출발": "인천(ICN)",
  "Column2": "뮌헨(MUC)",
  "Column3": 287,
  "Column4": 69960,
  "Column5": 3494
 },
 {
  "조회기간 : 2022.01 ~ 2022.12, 여객 : 전체, 화물 : 전체, 운항 : 전체, 노선 : 전체, 공항 : 인천(ICN), 상대공항 : 전체, 출발\/도착 : 출발": "인천(ICN)",
  "Column2": "타쉬켄트(TAS)",
  "Column3": 570,
  "Column4": 69325,
  "Column5": 11635
 },
 {
  "조회기간 : 2022.01 ~ 2022.12, 여객 : 전체, 화물 : 전체, 운항 : 전체, 노선 : 전체, 공항 : 인천(ICN), 상대공항 : 전체, 출발\/도착 : 출발": "인천(ICN)",
  "Column2": "디트로이트(DTW)",
  "Column3": 272,
  "Column4": 68733,
  "Column5": 4525
 },
 {
  "조회기간 : 2022.01 ~ 2022.12, 여객 : 전체, 화물 : 전체, 운항 : 전체, 노선 : 전체, 공항 : 인천(ICN), 상대공항 : 전체, 출발\/도착 : 출발": "인천(ICN)",
  "Column2": "암스텔담(AMS)",
  "Column3": 512,
  "Column4": 67721,
  "Column5": 14898
 },
 {
  "조회기간 : 2022.01 ~ 2022.12, 여객 : 전체, 화물 : 전체, 운항 : 전체, 노선 : 전체, 공항 : 인천(ICN), 상대공항 : 전체, 출발\/도착 : 출발": "인천(ICN)",
  "Column2": "코타키나발루(BKI)",
  "Column3": 377,
  "Column4": 56871,
  "Column5": 601
 },
 {
  "조회기간 : 2022.01 ~ 2022.12, 여객 : 전체, 화물 : 전체, 운항 : 전체, 노선 : 전체, 공항 : 인천(ICN), 상대공항 : 전체, 출발\/도착 : 출발": "인천(ICN)",
  "Column2": "워싱턴 둘리스(IAD)",
  "Column3": 319,
  "Column4": 53808,
  "Column5": 6941
 },
 {
  "조회기간 : 2022.01 ~ 2022.12, 여객 : 전체, 화물 : 전체, 운항 : 전체, 노선 : 전체, 공항 : 인천(ICN), 상대공항 : 전체, 출발\/도착 : 출발": "인천(ICN)",
  "Column2": "신치토세(CTS)",
  "Column3": 330,
  "Column4": 53062,
  "Column5": 523
 },
 {
  "조회기간 : 2022.01 ~ 2022.12, 여객 : 전체, 화물 : 전체, 운항 : 전체, 노선 : 전체, 공항 : 인천(ICN), 상대공항 : 전체, 출발\/도착 : 출발": "인천(ICN)",
  "Column2": "바르샤바(WAW)",
  "Column3": 240,
  "Column4": 51658,
  "Column5": 3464
 },
 {
  "조회기간 : 2022.01 ~ 2022.12, 여객 : 전체, 화물 : 전체, 운항 : 전체, 노선 : 전체, 공항 : 인천(ICN), 상대공항 : 전체, 출발\/도착 : 출발": "인천(ICN)",
  "Column2": "푸쿡(PQC)",
  "Column3": 290,
  "Column4": 50933,
  "Column5": 461
 },
 {
  "조회기간 : 2022.01 ~ 2022.12, 여객 : 전체, 화물 : 전체, 운항 : 전체, 노선 : 전체, 공항 : 인천(ICN), 상대공항 : 전체, 출발\/도착 : 출발": "인천(ICN)",
  "Column2": "덴파사(DPS)",
  "Column3": 201,
  "Column4": 50468,
  "Column5": 758
 },
 {
  "조회기간 : 2022.01 ~ 2022.12, 여객 : 전체, 화물 : 전체, 운항 : 전체, 노선 : 전체, 공항 : 인천(ICN), 상대공항 : 전체, 출발\/도착 : 출발": "인천(ICN)",
  "Column2": "칼리보(KLO)",
  "Column3": 320,
  "Column4": 49788,
  "Column5": 470
 },
 {
  "조회기간 : 2022.01 ~ 2022.12, 여객 : 전체, 화물 : 전체, 운항 : 전체, 노선 : 전체, 공항 : 인천(ICN), 상대공항 : 전체, 출발\/도착 : 출발": "인천(ICN)",
  "Column2": "알마아타(ALA)",
  "Column3": 290,
  "Column4": 46026,
  "Column5": 2352
 },
 {
  "조회기간 : 2022.01 ~ 2022.12, 여객 : 전체, 화물 : 전체, 운항 : 전체, 노선 : 전체, 공항 : 인천(ICN), 상대공항 : 전체, 출발\/도착 : 출발": "인천(ICN)",
  "Column2": "시카고(ORD)",
  "Column3": 1592,
  "Column4": 43031,
  "Column5": 72633
 },
 {
  "조회기간 : 2022.01 ~ 2022.12, 여객 : 전체, 화물 : 전체, 운항 : 전체, 노선 : 전체, 공항 : 인천(ICN), 상대공항 : 전체, 출발\/도착 : 출발": "인천(ICN)",
  "Column2": "나고야(NGO)",
  "Column3": 410,
  "Column4": 41208,
  "Column5": 23876
 },
 {
  "조회기간 : 2022.01 ~ 2022.12, 여객 : 전체, 화물 : 전체, 운항 : 전체, 노선 : 전체, 공항 : 인천(ICN), 상대공항 : 전체, 출발\/도착 : 출발": "인천(ICN)",
  "Column2": "델리(DEL)",
  "Column3": 288,
  "Column4": 39851,
  "Column5": 4586
 },
 {
  "조회기간 : 2022.01 ~ 2022.12, 여객 : 전체, 화물 : 전체, 운항 : 전체, 노선 : 전체, 공항 : 인천(ICN), 상대공항 : 전체, 출발\/도착 : 출발": "인천(ICN)",
  "Column2": "헬싱키(HEL)",
  "Column3": 219,
  "Column4": 39692,
  "Column5": 4075
 },
 {
  "조회기간 : 2022.01 ~ 2022.12, 여객 : 전체, 화물 : 전체, 운항 : 전체, 노선 : 전체, 공항 : 인천(ICN), 상대공항 : 전체, 출발\/도착 : 출발": "인천(ICN)",
  "Column2": "오클랜드(AKL)",
  "Column3": 190,
  "Column4": 35194,
  "Column5": 2521
 },
 {
  "조회기간 : 2022.01 ~ 2022.12, 여객 : 전체, 화물 : 전체, 운항 : 전체, 노선 : 전체, 공항 : 인천(ICN), 상대공항 : 전체, 출발\/도착 : 출발": "인천(ICN)",
  "Column2": "보스톤(BOS)",
  "Column3": 182,
  "Column4": 34305,
  "Column5": 2864
 },
 {
  "조회기간 : 2022.01 ~ 2022.12, 여객 : 전체, 화물 : 전체, 운항 : 전체, 노선 : 전체, 공항 : 인천(ICN), 상대공항 : 전체, 출발\/도착 : 출발": "인천(ICN)",
  "Column2": "푸켓(HKT)",
  "Column3": 195,
  "Column4": 33085,
  "Column5": 441
 },
 {
  "조회기간 : 2022.01 ~ 2022.12, 여객 : 전체, 화물 : 전체, 운항 : 전체, 노선 : 전체, 공항 : 인천(ICN), 상대공항 : 전체, 출발\/도착 : 출발": "인천(ICN)",
  "Column2": "청도(TAO)",
  "Column3": 736,
  "Column4": 29468,
  "Column5": 5532
 },
 {
  "조회기간 : 2022.01 ~ 2022.12, 여객 : 전체, 화물 : 전체, 운항 : 전체, 노선 : 전체, 공항 : 인천(ICN), 상대공항 : 전체, 출발\/도착 : 출발": "인천(ICN)",
  "Column2": "로마(FCO)",
  "Column3": 122,
  "Column4": 29320,
  "Column5": 974
 },
 {
  "조회기간 : 2022.01 ~ 2022.12, 여객 : 전체, 화물 : 전체, 운항 : 전체, 노선 : 전체, 공항 : 인천(ICN), 상대공항 : 전체, 출발\/도착 : 출발": "인천(ICN)",
  "Column2": "비엔티안(VTE)",
  "Column3": 244,
  "Column4": 28909,
  "Column5": 702
 },
 {
  "조회기간 : 2022.01 ~ 2022.12, 여객 : 전체, 화물 : 전체, 운항 : 전체, 노선 : 전체, 공항 : 인천(ICN), 상대공항 : 전체, 출발\/도착 : 출발": "인천(ICN)",
  "Column2": "치앙마이(CNX)",
  "Column3": 160,
  "Column4": 28154,
  "Column5": 453
 },
 {
  "조회기간 : 2022.01 ~ 2022.12, 여객 : 전체, 화물 : 전체, 운항 : 전체, 노선 : 전체, 공항 : 인천(ICN), 상대공항 : 전체, 출발\/도착 : 출발": "인천(ICN)",
  "Column2": "타크빌라란(TAG)",
  "Column3": 182,
  "Column4": 27717,
  "Column5": 310
 },
 {
  "조회기간 : 2022.01 ~ 2022.12, 여객 : 전체, 화물 : 전체, 운항 : 전체, 노선 : 전체, 공항 : 인천(ICN), 상대공항 : 전체, 출발\/도착 : 출발": "인천(ICN)",
  "Column2": "하이퐁(HPH)",
  "Column3": 155,
  "Column4": 26683,
  "Column5": 552
 },
 {
  "조회기간 : 2022.01 ~ 2022.12, 여객 : 전체, 화물 : 전체, 운항 : 전체, 노선 : 전체, 공항 : 인천(ICN), 상대공항 : 전체, 출발\/도착 : 출발": "인천(ICN)",
  "Column2": "부다페스트(BUD)",
  "Column3": 119,
  "Column4": 26569,
  "Column5": 3192
 },
 {
  "조회기간 : 2022.01 ~ 2022.12, 여객 : 전체, 화물 : 전체, 운항 : 전체, 노선 : 전체, 공항 : 인천(ICN), 상대공항 : 전체, 출발\/도착 : 출발": "인천(ICN)",
  "Column2": "바로셀로나(BCN)",
  "Column3": 100,
  "Column4": 23021,
  "Column5": 818
 },
 {
  "조회기간 : 2022.01 ~ 2022.12, 여객 : 전체, 화물 : 전체, 운항 : 전체, 노선 : 전체, 공항 : 인천(ICN), 상대공항 : 전체, 출발\/도착 : 출발": "인천(ICN)",
  "Column2": "김해(PUS)",
  "Column3": 186,
  "Column4": 20848,
  "Column5": 429
 },
 {
  "조회기간 : 2022.01 ~ 2022.12, 여객 : 전체, 화물 : 전체, 운항 : 전체, 노선 : 전체, 공항 : 인천(ICN), 상대공항 : 전체, 출발\/도착 : 출발": "인천(ICN)",
  "Column2": "아디스아바바(ADD)",
  "Column3": 153,
  "Column4": 19767,
  "Column5": 1516
 },
 {
  "조회기간 : 2022.01 ~ 2022.12, 여객 : 전체, 화물 : 전체, 운항 : 전체, 노선 : 전체, 공항 : 인천(ICN), 상대공항 : 전체, 출발\/도착 : 출발": "인천(ICN)",
  "Column2": "미네아폴리스(MSP)",
  "Column3": 89,
  "Column4": 19225,
  "Column5": 1254
 },
 {
  "조회기간 : 2022.01 ~ 2022.12, 여객 : 전체, 화물 : 전체, 운항 : 전체, 노선 : 전체, 공항 : 인천(ICN), 상대공항 : 전체, 출발\/도착 : 출발": "인천(ICN)",
  "Column2": "랑군(RGN)",
  "Column3": 223,
  "Column4": 18624,
  "Column5": 771
 },
 {
  "조회기간 : 2022.01 ~ 2022.12, 여객 : 전체, 화물 : 전체, 운항 : 전체, 노선 : 전체, 공항 : 인천(ICN), 상대공항 : 전체, 출발\/도착 : 출발": "인천(ICN)",
  "Column2": "비엔나(VIE)",
  "Column3": 84,
  "Column4": 17163,
  "Column5": 33292
 },
 {
  "조회기간 : 2022.01 ~ 2022.12, 여객 : 전체, 화물 : 전체, 운항 : 전체, 노선 : 전체, 공항 : 인천(ICN), 상대공항 : 전체, 출발\/도착 : 출발": "인천(ICN)",
  "Column2": "라스베가스(LAS)",
  "Column3": 87,
  "Column4": 16977,
  "Column5": 1010
 },
 {
  "조회기간 : 2022.01 ~ 2022.12, 여객 : 전체, 화물 : 전체, 운항 : 전체, 노선 : 전체, 공항 : 인천(ICN), 상대공항 : 전체, 출발\/도착 : 출발": "인천(ICN)",
  "Column2": "광저우(CAN)",
  "Column3": 673,
  "Column4": 16892,
  "Column5": 31143
 },
 {
  "조회기간 : 2022.01 ~ 2022.12, 여객 : 전체, 화물 : 전체, 운항 : 전체, 노선 : 전체, 공항 : 인천(ICN), 상대공항 : 전체, 출발\/도착 : 출발": "인천(ICN)",
  "Column2": "푸동(PVG)",
  "Column3": 2469,
  "Column4": 15392,
  "Column5": 90438
 },
 {
  "조회기간 : 2022.01 ~ 2022.12, 여객 : 전체, 화물 : 전체, 운항 : 전체, 노선 : 전체, 공항 : 인천(ICN), 상대공항 : 전체, 출발\/도착 : 출발": "인천(ICN)",
  "Column2": "심양(SHE)",
  "Column3": 129,
  "Column4": 15209,
  "Column5": 475
 },
 {
  "조회기간 : 2022.01 ~ 2022.12, 여객 : 전체, 화물 : 전체, 운항 : 전체, 노선 : 전체, 공항 : 인천(ICN), 상대공항 : 전체, 출발\/도착 : 출발": "인천(ICN)",
  "Column2": "오키나와(OKA)",
  "Column3": 101,
  "Column4": 14387,
  "Column5": 129
 },
 {
  "조회기간 : 2022.01 ~ 2022.12, 여객 : 전체, 화물 : 전체, 운항 : 전체, 노선 : 전체, 공항 : 인천(ICN), 상대공항 : 전체, 출발\/도착 : 출발": "인천(ICN)",
  "Column2": "밀라노(MXP)",
  "Column3": 564,
  "Column4": 13425,
  "Column5": 10856
 },
 {
  "조회기간 : 2022.01 ~ 2022.12, 여객 : 전체, 화물 : 전체, 운항 : 전체, 노선 : 전체, 공항 : 인천(ICN), 상대공항 : 전체, 출발\/도착 : 출발": "인천(ICN)",
  "Column2": "항조우(HGH)",
  "Column3": 126,
  "Column4": 11951,
  "Column5": 618
 },
 {
  "조회기간 : 2022.01 ~ 2022.12, 여객 : 전체, 화물 : 전체, 운항 : 전체, 노선 : 전체, 공항 : 인천(ICN), 상대공항 : 전체, 출발\/도착 : 출발": "인천(ICN)",
  "Column2": "난징(NKG)",
  "Column3": 86,
  "Column4": 11755,
  "Column5": 344
 },
 {
  "조회기간 : 2022.01 ~ 2022.12, 여객 : 전체, 화물 : 전체, 운항 : 전체, 노선 : 전체, 공항 : 인천(ICN), 상대공항 : 전체, 출발\/도착 : 출발": "인천(ICN)",
  "Column2": "장춘(CGQ)",
  "Column3": 47,
  "Column4": 11288,
  "Column5": 236
 },
 {
  "조회기간 : 2022.01 ~ 2022.12, 여객 : 전체, 화물 : 전체, 운항 : 전체, 노선 : 전체, 공항 : 인천(ICN), 상대공항 : 전체, 출발\/도착 : 출발": "인천(ICN)",
  "Column2": "북경(PEK)",
  "Column3": 307,
  "Column4": 10807,
  "Column5": 3625
 },
 {
  "조회기간 : 2022.01 ~ 2022.12, 여객 : 전체, 화물 : 전체, 운항 : 전체, 노선 : 전체, 공항 : 인천(ICN), 상대공항 : 전체, 출발\/도착 : 출발": "인천(ICN)",
  "Column2": "콜롬보(CMB)",
  "Column3": 64,
  "Column4": 10755,
  "Column5": 946
 },
 {
  "조회기간 : 2022.01 ~ 2022.12, 여객 : 전체, 화물 : 전체, 운항 : 전체, 노선 : 전체, 공항 : 인천(ICN), 상대공항 : 전체, 출발\/도착 : 출발": "인천(ICN)",
  "Column2": "카투만두(KTM)",
  "Column3": 97,
  "Column4": 10627,
  "Column5": 965
 },
 {
  "조회기간 : 2022.01 ~ 2022.12, 여객 : 전체, 화물 : 전체, 운항 : 전체, 노선 : 전체, 공항 : 인천(ICN), 상대공항 : 전체, 출발\/도착 : 출발": "인천(ICN)",
  "Column2": "센젠(SZX)",
  "Column3": 368,
  "Column4": 8829,
  "Column5": 13506
 },
 {
  "조회기간 : 2022.01 ~ 2022.12, 여객 : 전체, 화물 : 전체, 운항 : 전체, 노선 : 전체, 공항 : 인천(ICN), 상대공항 : 전체, 출발\/도착 : 출발": "인천(ICN)",
  "Column2": "샤먼(XMN)",
  "Column3": 253,
  "Column4": 8826,
  "Column5": 1463
 },
 {
  "조회기간 : 2022.01 ~ 2022.12, 여객 : 전체, 화물 : 전체, 운항 : 전체, 노선 : 전체, 공항 : 인천(ICN), 상대공항 : 전체, 출발\/도착 : 출발": "인천(ICN)",
  "Column2": "하얼빈(HRB)",
  "Column3": 70,
  "Column4": 8648,
  "Column5": 177
 },
 {
  "조회기간 : 2022.01 ~ 2022.12, 여객 : 전체, 화물 : 전체, 운항 : 전체, 노선 : 전체, 공항 : 인천(ICN), 상대공항 : 전체, 출발\/도착 : 출발": "인천(ICN)",
  "Column2": "하네다(HND)",
  "Column3": 63,
  "Column4": 8532,
  "Column5": 81
 },
 {
  "조회기간 : 2022.01 ~ 2022.12, 여객 : 전체, 화물 : 전체, 운항 : 전체, 노선 : 전체, 공항 : 인천(ICN), 상대공항 : 전체, 출발\/도착 : 출발": "인천(ICN)",
  "Column2": "리야드(RUH)",
  "Column3": 37,
  "Column4": 8152,
  "Column5": 1362
 },
 {
  "조회기간 : 2022.01 ~ 2022.12, 여객 : 전체, 화물 : 전체, 운항 : 전체, 노선 : 전체, 공항 : 인천(ICN), 상대공항 : 전체, 출발\/도착 : 출발": "인천(ICN)",
  "Column2": "대련(DLC)",
  "Column3": 526,
  "Column4": 7969,
  "Column5": 4878
 },
 {
  "조회기간 : 2022.01 ~ 2022.12, 여객 : 전체, 화물 : 전체, 운항 : 전체, 노선 : 전체, 공항 : 인천(ICN), 상대공항 : 전체, 출발\/도착 : 출발": "인천(ICN)",
  "Column2": "연대(YNT)",
  "Column3": 1212,
  "Column4": 7464,
  "Column5": 12672
 },
 {
  "조회기간 : 2022.01 ~ 2022.12, 여객 : 전체, 화물 : 전체, 운항 : 전체, 노선 : 전체, 공항 : 인천(ICN), 상대공항 : 전체, 출발\/도착 : 출발": "인천(ICN)",
  "Column2": "웨이하이(WEH)",
  "Column3": 468,
  "Column4": 6979,
  "Column5": 3348
 },
 {
  "조회기간 : 2022.01 ~ 2022.12, 여객 : 전체, 화물 : 전체, 운항 : 전체, 노선 : 전체, 공항 : 인천(ICN), 상대공항 : 전체, 출발\/도착 : 출발": "인천(ICN)",
  "Column2": "천진(TSN)",
  "Column3": 630,
  "Column4": 6731,
  "Column5": 28146
 },
 {
  "조회기간 : 2022.01 ~ 2022.12, 여객 : 전체, 화물 : 전체, 운항 : 전체, 노선 : 전체, 공항 : 인천(ICN), 상대공항 : 전체, 출발\/도착 : 출발": "인천(ICN)",
  "Column2": "멕시코(MEX)",
  "Column3": 43,
  "Column4": 6286,
  "Column5": 656
 },
 {
  "조회기간 : 2022.01 ~ 2022.12, 여객 : 전체, 화물 : 전체, 운항 : 전체, 노선 : 전체, 공항 : 인천(ICN), 상대공항 : 전체, 출발\/도착 : 출발": "인천(ICN)",
  "Column2": "우한(무한)(WUH)",
  "Column3": 244,
  "Column4": 5202,
  "Column5": 1758
 },
 {
  "조회기간 : 2022.01 ~ 2022.12, 여객 : 전체, 화물 : 전체, 운항 : 전체, 노선 : 전체, 공항 : 인천(ICN), 상대공항 : 전체, 출발\/도착 : 출발": "인천(ICN)",
  "Column2": "지난(TNA)",
  "Column3": 40,
  "Column4": 5142,
  "Column5": 144
 },
 {
  "조회기간 : 2022.01 ~ 2022.12, 여객 : 전체, 화물 : 전체, 운항 : 전체, 노선 : 전체, 공항 : 인천(ICN), 상대공항 : 전체, 출발\/도착 : 출발": "인천(ICN)",
  "Column2": "다카(DAC)",
  "Column3": 52,
  "Column4": 4212,
  "Column5": 222
 },
 {
  "조회기간 : 2022.01 ~ 2022.12, 여객 : 전체, 화물 : 전체, 운항 : 전체, 노선 : 전체, 공항 : 인천(ICN), 상대공항 : 전체, 출발\/도착 : 출발": "인천(ICN)",
  "Column2": "앙카라(ESB)",
  "Column3": 13,
  "Column4": 3492,
  "Column5": 50
 },
 {
  "조회기간 : 2022.01 ~ 2022.12, 여객 : 전체, 화물 : 전체, 운항 : 전체, 노선 : 전체, 공항 : 인천(ICN), 상대공항 : 전체, 출발\/도착 : 출발": "인천(ICN)",
  "Column2": "제다(JED)",
  "Column3": 60,
  "Column4": 3121,
  "Column5": 415
 },
 {
  "조회기간 : 2022.01 ~ 2022.12, 여객 : 전체, 화물 : 전체, 운항 : 전체, 노선 : 전체, 공항 : 인천(ICN), 상대공항 : 전체, 출발\/도착 : 출발": "인천(ICN)",
  "Column2": "다가마스(TAK)",
  "Column3": 17,
  "Column4": 3078,
  "Column5": 27
 },
 {
  "조회기간 : 2022.01 ~ 2022.12, 여객 : 전체, 화물 : 전체, 운항 : 전체, 노선 : 전체, 공항 : 인천(ICN), 상대공항 : 전체, 출발\/도착 : 출발": "인천(ICN)",
  "Column2": "블라디보스토크(VVO)",
  "Column3": 40,
  "Column4": 2849,
  "Column5": 94
 },
 {
  "조회기간 : 2022.01 ~ 2022.12, 여객 : 전체, 화물 : 전체, 운항 : 전체, 노선 : 전체, 공항 : 인천(ICN), 상대공항 : 전체, 출발\/도착 : 출발": "인천(ICN)",
  "Column2": "달랏(DLI)",
  "Column3": 18,
  "Column4": 2404,
  "Column5": 34
 },
 {
  "조회기간 : 2022.01 ~ 2022.12, 여객 : 전체, 화물 : 전체, 운항 : 전체, 노선 : 전체, 공항 : 인천(ICN), 상대공항 : 전체, 출발\/도착 : 출발": "인천(ICN)",
  "Column2": "모스코바(SVO)",
  "Column3": 84,
  "Column4": 2393,
  "Column5": 3167
 },
 {
  "조회기간 : 2022.01 ~ 2022.12, 여객 : 전체, 화물 : 전체, 운항 : 전체, 노선 : 전체, 공항 : 인천(ICN), 상대공항 : 전체, 출발\/도착 : 출발": "인천(ICN)",
  "Column2": "시안(XIY)",
  "Column3": 352,
  "Column4": 1784,
  "Column5": 7222
 },
 {
  "조회기간 : 2022.01 ~ 2022.12, 여객 : 전체, 화물 : 전체, 운항 : 전체, 노선 : 전체, 공항 : 인천(ICN), 상대공항 : 전체, 출발\/도착 : 출발": "인천(ICN)",
  "Column2": "인천(ICN)",
  "Column3": 15,
  "Column4": 1750,
  "Column5": 1
 },
 {
  "조회기간 : 2022.01 ~ 2022.12, 여객 : 전체, 화물 : 전체, 운항 : 전체, 노선 : 전체, 공항 : 인천(ICN), 상대공항 : 전체, 출발\/도착 : 출발": "인천(ICN)",
  "Column2": "청두(CTU)",
  "Column3": 286,
  "Column4": 1594,
  "Column5": 2800
 },
 {
  "조회기간 : 2022.01 ~ 2022.12, 여객 : 전체, 화물 : 전체, 운항 : 전체, 노선 : 전체, 공항 : 인천(ICN), 상대공항 : 전체, 출발\/도착 : 출발": "인천(ICN)",
  "Column2": "반다르세리베가완(BWN)",
  "Column3": 14,
  "Column4": 1107,
  "Column5": 23
 },
 {
  "조회기간 : 2022.01 ~ 2022.12, 여객 : 전체, 화물 : 전체, 운항 : 전체, 노선 : 전체, 공항 : 인천(ICN), 상대공항 : 전체, 출발\/도착 : 출발": "인천(ICN)",
  "Column2": "총킹(중경)(CKG)",
  "Column3": 100,
  "Column4": 892,
  "Column5": 1079
 },
 {
  "조회기간 : 2022.01 ~ 2022.12, 여객 : 전체, 화물 : 전체, 운항 : 전체, 노선 : 전체, 공항 : 인천(ICN), 상대공항 : 전체, 출발\/도착 : 출발": "인천(ICN)",
  "Column2": "마나스(FRU)",
  "Column3": 22,
  "Column4": 858,
  "Column5": 89
 },
 {
  "조회기간 : 2022.01 ~ 2022.12, 여객 : 전체, 화물 : 전체, 운항 : 전체, 노선 : 전체, 공항 : 인천(ICN), 상대공항 : 전체, 출발\/도착 : 출발": "인천(ICN)",
  "Column2": "껀터(VCA)",
  "Column3": 5,
  "Column4": 825,
  "Column5": 13
 },
 {
  "조회기간 : 2022.01 ~ 2022.12, 여객 : 전체, 화물 : 전체, 운항 : 전체, 노선 : 전체, 공항 : 인천(ICN), 상대공항 : 전체, 출발\/도착 : 출발": "인천(ICN)",
  "Column2": "씨엠립(REP)",
  "Column3": 4,
  "Column4": 824,
  "Column5": 7
 },
 {
  "조회기간 : 2022.01 ~ 2022.12, 여객 : 전체, 화물 : 전체, 운항 : 전체, 노선 : 전체, 공항 : 인천(ICN), 상대공항 : 전체, 출발\/도착 : 출발": "인천(ICN)",
  "Column2": "두브로브니크(DBV)",
  "Column3": 3,
  "Column4": 633,
  "Column5": 12
 },
 {
  "조회기간 : 2022.01 ~ 2022.12, 여객 : 전체, 화물 : 전체, 운항 : 전체, 노선 : 전체, 공항 : 인천(ICN), 상대공항 : 전체, 출발\/도착 : 출발": "인천(ICN)",
  "Column2": "노보시비르스크(OVB)",
  "Column3": 9,
  "Column4": 612,
  "Column5": 30
 },
 {
  "조회기간 : 2022.01 ~ 2022.12, 여객 : 전체, 화물 : 전체, 운항 : 전체, 노선 : 전체, 공항 : 인천(ICN), 상대공항 : 전체, 출발\/도착 : 출발": "인천(ICN)",
  "Column2": "텔아비브(TLV)",
  "Column3": 5,
  "Column4": 606,
  "Column5": 60
 },
 {
  "조회기간 : 2022.01 ~ 2022.12, 여객 : 전체, 화물 : 전체, 운항 : 전체, 노선 : 전체, 공항 : 인천(ICN), 상대공항 : 전체, 출발\/도착 : 출발": "인천(ICN)",
  "Column2": "미와사키(KMI)",
  "Column3": 3,
  "Column4": 425,
  "Column5": 5
 },
 {
  "조회기간 : 2022.01 ~ 2022.12, 여객 : 전체, 화물 : 전체, 운항 : 전체, 노선 : 전체, 공항 : 인천(ICN), 상대공항 : 전체, 출발\/도착 : 출발": "인천(ICN)",
  "Column2": "베이루트(BEY)",
  "Column3": 3,
  "Column4": 340,
  "Column5": 27
 },
 {
  "조회기간 : 2022.01 ~ 2022.12, 여객 : 전체, 화물 : 전체, 운항 : 전체, 노선 : 전체, 공항 : 인천(ICN), 상대공항 : 전체, 출발\/도착 : 출발": "인천(ICN)",
  "Column2": "첸나이(MAA)",
  "Column3": 5,
  "Column4": 331,
  "Column5": 130
 },
 {
  "조회기간 : 2022.01 ~ 2022.12, 여객 : 전체, 화물 : 전체, 운항 : 전체, 노선 : 전체, 공항 : 인천(ICN), 상대공항 : 전체, 출발\/도착 : 출발": "인천(ICN)",
  "Column2": "파라구에(PRG)",
  "Column3": 3,
  "Column4": 246,
  "Column5": 39
 },
 {
  "조회기간 : 2022.01 ~ 2022.12, 여객 : 전체, 화물 : 전체, 운항 : 전체, 노선 : 전체, 공항 : 인천(ICN), 상대공항 : 전체, 출발\/도착 : 출발": "인천(ICN)",
  "Column2": "뱅갈로(BLR)",
  "Column3": 2,
  "Column4": 237,
  "Column5": 15
 },
 {
  "조회기간 : 2022.01 ~ 2022.12, 여객 : 전체, 화물 : 전체, 운항 : 전체, 노선 : 전체, 공항 : 인천(ICN), 상대공항 : 전체, 출발\/도착 : 출발": "인천(ICN)",
  "Column2": "빈 국제공항(VII)",
  "Column3": 1,
  "Column4": 217,
  "Column5": 6
 },
 {
  "조회기간 : 2022.01 ~ 2022.12, 여객 : 전체, 화물 : 전체, 운항 : 전체, 노선 : 전체, 공항 : 인천(ICN), 상대공항 : 전체, 출발\/도착 : 출발": "인천(ICN)",
  "Column2": "번돈(VDO)",
  "Column3": 1,
  "Column4": 116,
  "Column5": 1
 },
 {
  "조회기간 : 2022.01 ~ 2022.12, 여객 : 전체, 화물 : 전체, 운항 : 전체, 노선 : 전체, 공항 : 인천(ICN), 상대공항 : 전체, 출발\/도착 : 출발": "인천(ICN)",
  "Column2": "연길(YNJ)",
  "Column3": 9,
  "Column4": 88,
  "Column5": 1
 },
 {
  "조회기간 : 2022.01 ~ 2022.12, 여객 : 전체, 화물 : 전체, 운항 : 전체, 노선 : 전체, 공항 : 인천(ICN), 상대공항 : 전체, 출발\/도착 : 출발": "인천(ICN)",
  "Column2": "타이유안(TYN)",
  "Column3": 1,
  "Column4": 36,
  "Column5": 1
 },
 {
  "조회기간 : 2022.01 ~ 2022.12, 여객 : 전체, 화물 : 전체, 운항 : 전체, 노선 : 전체, 공항 : 인천(ICN), 상대공항 : 전체, 출발\/도착 : 출발": "인천(ICN)",
  "Column2": "과달라하라(GDL)",
  "Column3": 157,
  "Column4": 0,
  "Column5": 2516
 },
 {
  "조회기간 : 2022.01 ~ 2022.12, 여객 : 전체, 화물 : 전체, 운항 : 전체, 노선 : 전체, 공항 : 인천(ICN), 상대공항 : 전체, 출발\/도착 : 출발": "인천(ICN)",
  "Column2": "그린빌-스파르탄버그(GSP)",
  "Column3": 14,
  "Column4": 0,
  "Column5": 206
 },
 {
  "조회기간 : 2022.01 ~ 2022.12, 여객 : 전체, 화물 : 전체, 운항 : 전체, 노선 : 전체, 공항 : 인천(ICN), 상대공항 : 전체, 출발\/도착 : 출발": "인천(ICN)",
  "Column2": "나보이(NVI)",
  "Column3": 1,
  "Column4": 0,
  "Column5": 83
 },
 {
  "조회기간 : 2022.01 ~ 2022.12, 여객 : 전체, 화물 : 전체, 운항 : 전체, 노선 : 전체, 공항 : 인천(ICN), 상대공항 : 전체, 출발\/도착 : 출발": "인천(ICN)",
  "Column2": "노팅햄이스트미들랜드(EMA)",
  "Column3": 14,
  "Column4": 0,
  "Column5": 113
 },
 {
  "조회기간 : 2022.01 ~ 2022.12, 여객 : 전체, 화물 : 전체, 운항 : 전체, 노선 : 전체, 공항 : 인천(ICN), 상대공항 : 전체, 출발\/도착 : 출발": "인천(ICN)",
  "Column2": "뉴왁(EWR)",
  "Column3": 53,
  "Column4": 0,
  "Column5": 0
 },
 {
  "조회기간 : 2022.01 ~ 2022.12, 여객 : 전체, 화물 : 전체, 운항 : 전체, 노선 : 전체, 공항 : 인천(ICN), 상대공항 : 전체, 출발\/도착 : 출발": "인천(ICN)",
  "Column2": "닝보(NGB)",
  "Column3": 2,
  "Column4": 0,
  "Column5": 0
 },
 {
  "조회기간 : 2022.01 ~ 2022.12, 여객 : 전체, 화물 : 전체, 운항 : 전체, 노선 : 전체, 공항 : 인천(ICN), 상대공항 : 전체, 출발\/도착 : 출발": "인천(ICN)",
  "Column2": "라이프치히(LEJ)",
  "Column3": 834,
  "Column4": 0,
  "Column5": 315
 },
 {
  "조회기간 : 2022.01 ~ 2022.12, 여객 : 전체, 화물 : 전체, 운항 : 전체, 노선 : 전체, 공항 : 인천(ICN), 상대공항 : 전체, 출발\/도착 : 출발": "인천(ICN)",
  "Column2": "루이즈빌(SDF)",
  "Column3": 279,
  "Column4": 0,
  "Column5": 11
 },
 {
  "조회기간 : 2022.01 ~ 2022.12, 여객 : 전체, 화물 : 전체, 운항 : 전체, 노선 : 전체, 공항 : 인천(ICN), 상대공항 : 전체, 출발\/도착 : 출발": "인천(ICN)",
  "Column2": "룩셈부르크(LUX)",
  "Column3": 167,
  "Column4": 0,
  "Column5": 14693
 },
 {
  "조회기간 : 2022.01 ~ 2022.12, 여객 : 전체, 화물 : 전체, 운항 : 전체, 노선 : 전체, 공항 : 인천(ICN), 상대공항 : 전체, 출발\/도착 : 출발": "인천(ICN)",
  "Column2": "리에쥬 비어셋(LGG)",
  "Column3": 2,
  "Column4": 0,
  "Column5": 132
 },
 {
  "조회기간 : 2022.01 ~ 2022.12, 여객 : 전체, 화물 : 전체, 운항 : 전체, 노선 : 전체, 공항 : 인천(ICN), 상대공항 : 전체, 출발\/도착 : 출발": "인천(ICN)",
  "Column2": "리켄백(LCK)",
  "Column3": 265,
  "Column4": 0,
  "Column5": 8616
 },
 {
  "조회기간 : 2022.01 ~ 2022.12, 여객 : 전체, 화물 : 전체, 운항 : 전체, 노선 : 전체, 공항 : 인천(ICN), 상대공항 : 전체, 출발\/도착 : 출발": "인천(ICN)",
  "Column2": "마드리드(MAD)",
  "Column3": 127,
  "Column4": 0,
  "Column5": 7724
 },
 {
  "조회기간 : 2022.01 ~ 2022.12, 여객 : 전체, 화물 : 전체, 운항 : 전체, 노선 : 전체, 공항 : 인천(ICN), 상대공항 : 전체, 출발\/도착 : 출발": "인천(ICN)",
  "Column2": "마르켈쿤하마차도(SLZ)",
  "Column3": 1,
  "Column4": 0,
  "Column5": 18
 },
 {
  "조회기간 : 2022.01 ~ 2022.12, 여객 : 전체, 화물 : 전체, 운항 : 전체, 노선 : 전체, 공항 : 인천(ICN), 상대공항 : 전체, 출발\/도착 : 출발": "인천(ICN)",
  "Column2": "마이애미(MIA)",
  "Column3": 395,
  "Column4": 0,
  "Column5": 14613
 },
 {
  "조회기간 : 2022.01 ~ 2022.12, 여객 : 전체, 화물 : 전체, 운항 : 전체, 노선 : 전체, 공항 : 인천(ICN), 상대공항 : 전체, 출발\/도착 : 출발": "인천(ICN)",
  "Column2": "마푸트 국제공항(MPM)",
  "Column3": 1,
  "Column4": 0,
  "Column5": 46
 },
 {
  "조회기간 : 2022.01 ~ 2022.12, 여객 : 전체, 화물 : 전체, 운항 : 전체, 노선 : 전체, 공항 : 인천(ICN), 상대공항 : 전체, 출발\/도착 : 출발": "인천(ICN)",
  "Column2": "맥코넬 공군기지(IAB)",
  "Column3": 1,
  "Column4": 0,
  "Column5": 20
 },
 {
  "조회기간 : 2022.01 ~ 2022.12, 여객 : 전체, 화물 : 전체, 운항 : 전체, 노선 : 전체, 공항 : 인천(ICN), 상대공항 : 전체, 출발\/도착 : 출발": "인천(ICN)",
  "Column2": "멤피스(MEM)",
  "Column3": 425,
  "Column4": 0,
  "Column5": 11
 },
 {
  "조회기간 : 2022.01 ~ 2022.12, 여객 : 전체, 화물 : 전체, 운항 : 전체, 노선 : 전체, 공항 : 인천(ICN), 상대공항 : 전체, 출발\/도착 : 출발": "인천(ICN)",
  "Column2": "몬트리올(YUL)",
  "Column3": 12,
  "Column4": 0,
  "Column5": 39
 },
 {
  "조회기간 : 2022.01 ~ 2022.12, 여객 : 전체, 화물 : 전체, 운항 : 전체, 노선 : 전체, 공항 : 인천(ICN), 상대공항 : 전체, 출발\/도착 : 출발": "인천(ICN)",
  "Column2": "보리스필(KBP)",
  "Column3": 4,
  "Column4": 0,
  "Column5": 37
 },
 {
  "조회기간 : 2022.01 ~ 2022.12, 여객 : 전체, 화물 : 전체, 운항 : 전체, 노선 : 전체, 공항 : 인천(ICN), 상대공항 : 전체, 출발\/도착 : 출발": "인천(ICN)",
  "Column2": "브라코프스(VCP)",
  "Column3": 152,
  "Column4": 0,
  "Column5": 3165
 },
 {
  "조회기간 : 2022.01 ~ 2022.12, 여객 : 전체, 화물 : 전체, 운항 : 전체, 노선 : 전체, 공항 : 인천(ICN), 상대공항 : 전체, 출발\/도착 : 출발": "인천(ICN)",
  "Column2": "브로츠와프(WRO)",
  "Column3": 1,
  "Column4": 0,
  "Column5": 40
 },
 {
  "조회기간 : 2022.01 ~ 2022.12, 여객 : 전체, 화물 : 전체, 운항 : 전체, 노선 : 전체, 공항 : 인천(ICN), 상대공항 : 전체, 출발\/도착 : 출발": "인천(ICN)",
  "Column2": "브뤼셀(BRU)",
  "Column3": 157,
  "Column4": 0,
  "Column5": 54
 },
 {
  "조회기간 : 2022.01 ~ 2022.12, 여객 : 전체, 화물 : 전체, 운항 : 전체, 노선 : 전체, 공항 : 인천(ICN), 상대공항 : 전체, 출발\/도착 : 출발": "인천(ICN)",
  "Column2": "샤론스(XCR)",
  "Column3": 1,
  "Column4": 0,
  "Column5": 13
 },
 {
  "조회기간 : 2022.01 ~ 2022.12, 여객 : 전체, 화물 : 전체, 운항 : 전체, 노선 : 전체, 공항 : 인천(ICN), 상대공항 : 전체, 출발\/도착 : 출발": "인천(ICN)",
  "Column2": "샤자르(SHJ)",
  "Column3": 3,
  "Column4": 0,
  "Column5": 76
 },
 {
  "조회기간 : 2022.01 ~ 2022.12, 여객 : 전체, 화물 : 전체, 운항 : 전체, 노선 : 전체, 공항 : 인천(ICN), 상대공항 : 전체, 출발\/도착 : 출발": "인천(ICN)",
  "Column2": "스톡홀름 알란다(ARN)",
  "Column3": 41,
  "Column4": 0,
  "Column5": 115
 },
 {
  "조회기간 : 2022.01 ~ 2022.12, 여객 : 전체, 화물 : 전체, 운항 : 전체, 노선 : 전체, 공항 : 인천(ICN), 상대공항 : 전체, 출발\/도착 : 출발": "인천(ICN)",
  "Column2": "시카고 록퍼드 국제공항(RFD)",
  "Column3": 440,
  "Column4": 0,
  "Column5": 13617
 },
 {
  "조회기간 : 2022.01 ~ 2022.12, 여객 : 전체, 화물 : 전체, 운항 : 전체, 노선 : 전체, 공항 : 인천(ICN), 상대공항 : 전체, 출발\/도착 : 출발": "인천(ICN)",
  "Column2": "신시내티(CVG)",
  "Column3": 1136,
  "Column4": 0,
  "Column5": 1370
 },
 {
  "조회기간 : 2022.01 ~ 2022.12, 여객 : 전체, 화물 : 전체, 운항 : 전체, 노선 : 전체, 공항 : 인천(ICN), 상대공항 : 전체, 출발\/도착 : 출발": "인천(ICN)",
  "Column2": "알 막툼(DWC)",
  "Column3": 6,
  "Column4": 0,
  "Column5": 255
 },
 {
  "조회기간 : 2022.01 ~ 2022.12, 여객 : 전체, 화물 : 전체, 운항 : 전체, 노선 : 전체, 공항 : 인천(ICN), 상대공항 : 전체, 출발\/도착 : 출발": "인천(ICN)",
  "Column2": "앵커리지(ANC)",
  "Column3": 4425,
  "Column4": 0,
  "Column5": 41416
 },
 {
  "조회기간 : 2022.01 ~ 2022.12, 여객 : 전체, 화물 : 전체, 운항 : 전체, 노선 : 전체, 공항 : 인천(ICN), 상대공항 : 전체, 출발\/도착 : 출발": "인천(ICN)",
  "Column2": "에드먼튼(YEG)",
  "Column3": 2,
  "Column4": 0,
  "Column5": 49
 },
 {
  "조회기간 : 2022.01 ~ 2022.12, 여객 : 전체, 화물 : 전체, 운항 : 전체, 노선 : 전체, 공항 : 인천(ICN), 상대공항 : 전체, 출발\/도착 : 출발": "인천(ICN)",
  "Column2": "오슬로(OSL)",
  "Column3": 117,
  "Column4": 0,
  "Column5": 604
 },
 {
  "조회기간 : 2022.01 ~ 2022.12, 여객 : 전체, 화물 : 전체, 운항 : 전체, 노선 : 전체, 공항 : 인천(ICN), 상대공항 : 전체, 출발\/도착 : 출발": "인천(ICN)",
  "Column2": "온타리오(ONT)",
  "Column3": 24,
  "Column4": 0,
  "Column5": 0
 },
 {
  "조회기간 : 2022.01 ~ 2022.12, 여객 : 전체, 화물 : 전체, 운항 : 전체, 노선 : 전체, 공항 : 인천(ICN), 상대공항 : 전체, 출발\/도착 : 출발": "인천(ICN)",
  "Column2": "와가두구 공항(OUA)",
  "Column3": 1,
  "Column4": 0,
  "Column5": 23
 },
 {
  "조회기간 : 2022.01 ~ 2022.12, 여객 : 전체, 화물 : 전체, 운항 : 전체, 노선 : 전체, 공항 : 인천(ICN), 상대공항 : 전체, 출발\/도착 : 출발": "인천(ICN)",
  "Column2": "우시샤우팡(WUX)",
  "Column3": 18,
  "Column4": 0,
  "Column5": 1085
 },
 {
  "조회기간 : 2022.01 ~ 2022.12, 여객 : 전체, 화물 : 전체, 운항 : 전체, 노선 : 전체, 공항 : 인천(ICN), 상대공항 : 전체, 출발\/도착 : 출발": "인천(ICN)",
  "Column2": "우즈호로드(UDJ)",
  "Column3": 2,
  "Column4": 0,
  "Column5": 0
 },
 {
  "조회기간 : 2022.01 ~ 2022.12, 여객 : 전체, 화물 : 전체, 운항 : 전체, 노선 : 전체, 공항 : 인천(ICN), 상대공항 : 전체, 출발\/도착 : 출발": "인천(ICN)",
  "Column2": "울란도(MCO)",
  "Column3": 1,
  "Column4": 0,
  "Column5": 34
 },
 {
  "조회기간 : 2022.01 ~ 2022.12, 여객 : 전체, 화물 : 전체, 운항 : 전체, 노선 : 전체, 공항 : 인천(ICN), 상대공항 : 전체, 출발\/도착 : 출발": "인천(ICN)",
  "Column2": "원저우(WNZ)",
  "Column3": 4,
  "Column4": 0,
  "Column5": 1
 },
 {
  "조회기간 : 2022.01 ~ 2022.12, 여객 : 전체, 화물 : 전체, 운항 : 전체, 노선 : 전체, 공항 : 인천(ICN), 상대공항 : 전체, 출발\/도착 : 출발": "인천(ICN)",
  "Column2": "이루크츠크(IKT)",
  "Column3": 2,
  "Column4": 0,
  "Column5": 37
 },
 {
  "조회기간 : 2022.01 ~ 2022.12, 여객 : 전체, 화물 : 전체, 운항 : 전체, 노선 : 전체, 공항 : 인천(ICN), 상대공항 : 전체, 출발\/도착 : 출발": "인천(ICN)",
  "Column2": "이스탄불(ISL)",
  "Column3": 11,
  "Column4": 0,
  "Column5": 765
 },
 {
  "조회기간 : 2022.01 ~ 2022.12, 여객 : 전체, 화물 : 전체, 운항 : 전체, 노선 : 전체, 공항 : 인천(ICN), 상대공항 : 전체, 출발\/도착 : 출발": "인천(ICN)",
  "Column2": "인디아나폴리스(IND)",
  "Column3": 450,
  "Column4": 0,
  "Column5": 0
 },
 {
  "조회기간 : 2022.01 ~ 2022.12, 여객 : 전체, 화물 : 전체, 운항 : 전체, 노선 : 전체, 공항 : 인천(ICN), 상대공항 : 전체, 출발\/도착 : 출발": "인천(ICN)",
  "Column2": "정저우(CGO)",
  "Column3": 391,
  "Column4": 0,
  "Column5": 5915
 },
 {
  "조회기간 : 2022.01 ~ 2022.12, 여객 : 전체, 화물 : 전체, 운항 : 전체, 노선 : 전체, 공항 : 인천(ICN), 상대공항 : 전체, 출발\/도착 : 출발": "인천(ICN)",
  "Column2": "제슈프 공항(RZE)",
  "Column3": 1,
  "Column4": 0,
  "Column5": 55
 },
 {
  "조회기간 : 2022.01 ~ 2022.12, 여객 : 전체, 화물 : 전체, 운항 : 전체, 노선 : 전체, 공항 : 인천(ICN), 상대공항 : 전체, 출발\/도착 : 출발": "인천(ICN)",
  "Column2": "취리히(ZRH)",
  "Column3": 52,
  "Column4": 0,
  "Column5": 48
 },
 {
  "조회기간 : 2022.01 ~ 2022.12, 여객 : 전체, 화물 : 전체, 운항 : 전체, 노선 : 전체, 공항 : 인천(ICN), 상대공항 : 전체, 출발\/도착 : 출발": "인천(ICN)",
  "Column2": "카툼(KRT)",
  "Column3": 1,
  "Column4": 0,
  "Column5": 25
 },
 {
  "조회기간 : 2022.01 ~ 2022.12, 여객 : 전체, 화물 : 전체, 운항 : 전체, 노선 : 전체, 공항 : 인천(ICN), 상대공항 : 전체, 출발\/도착 : 출발": "인천(ICN)",
  "Column2": "캘거리(YYC)",
  "Column3": 13,
  "Column4": 0,
  "Column5": 191
 },
 {
  "조회기간 : 2022.01 ~ 2022.12, 여객 : 전체, 화물 : 전체, 운항 : 전체, 노선 : 전체, 공항 : 인천(ICN), 상대공항 : 전체, 출발\/도착 : 출발": "인천(ICN)",
  "Column2": "퀼른(CGN)",
  "Column3": 5,
  "Column4": 0,
  "Column5": 5842
 },
 {
  "조회기간 : 2022.01 ~ 2022.12, 여객 : 전체, 화물 : 전체, 운항 : 전체, 노선 : 전체, 공항 : 인천(ICN), 상대공항 : 전체, 출발\/도착 : 출발": "인천(ICN)",
  "Column2": "크라스노얄스크(KJA)",
  "Column3": 7,
  "Column4": 0,
  "Column5": 112
 },
 {
  "조회기간 : 2022.01 ~ 2022.12, 여객 : 전체, 화물 : 전체, 운항 : 전체, 노선 : 전체, 공항 : 인천(ICN), 상대공항 : 전체, 출발\/도착 : 출발": "인천(ICN)",
  "Column2": "키타큐슈(KKJ)",
  "Column3": 188,
  "Column4": 0,
  "Column5": 5362
 },
 {
  "조회기간 : 2022.01 ~ 2022.12, 여객 : 전체, 화물 : 전체, 운항 : 전체, 노선 : 전체, 공항 : 인천(ICN), 상대공항 : 전체, 출발\/도착 : 출발": "인천(ICN)",
  "Column2": "퍼스(PER)",
  "Column3": 3,
  "Column4": 0,
  "Column5": 180
 },
 {
  "조회기간 : 2022.01 ~ 2022.12, 여객 : 전체, 화물 : 전체, 운항 : 전체, 노선 : 전체, 공항 : 인천(ICN), 상대공항 : 전체, 출발\/도착 : 출발": "인천(ICN)",
  "Column2": "페낭(PEN)",
  "Column3": 363,
  "Column4": 0,
  "Column5": 10214
 },
 {
  "조회기간 : 2022.01 ~ 2022.12, 여객 : 전체, 화물 : 전체, 운항 : 전체, 노선 : 전체, 공항 : 인천(ICN), 상대공항 : 전체, 출발\/도착 : 출발": "인천(ICN)",
  "Column2": "푸조우(FOC)",
  "Column3": 3,
  "Column4": 0,
  "Column5": 0
 },
 {
  "조회기간 : 2022.01 ~ 2022.12, 여객 : 전체, 화물 : 전체, 운항 : 전체, 노선 : 전체, 공항 : 인천(ICN), 상대공항 : 전체, 출발\/도착 : 출발": "인천(ICN)",
  "Column2": "프레스트윅(PIK)",
  "Column3": 1,
  "Column4": 0,
  "Column5": 26
 },
 {
  "조회기간 : 2022.01 ~ 2022.12, 여객 : 전체, 화물 : 전체, 운항 : 전체, 노선 : 전체, 공항 : 인천(ICN), 상대공항 : 전체, 출발\/도착 : 출발": "인천(ICN)",
  "Column2": "허폐(HFE)",
  "Column3": 111,
  "Column4": 0,
  "Column5": 777
 },
 {
  "조회기간 : 2022.01 ~ 2022.12, 여객 : 전체, 화물 : 전체, 운항 : 전체, 노선 : 전체, 공항 : 인천(ICN), 상대공항 : 전체, 출발\/도착 : 출발": "인천(ICN)",
  "Column2": "헤이다르 알리예프(GYD)",
  "Column3": 168,
  "Column4": 0,
  "Column5": 12547
 },
 {
  "조회기간 : 2022.01 ~ 2022.12, 여객 : 전체, 화물 : 전체, 운항 : 전체, 노선 : 전체, 공항 : 인천(ICN), 상대공항 : 전체, 출발\/도착 : 출발": "인천(ICN)",
  "Column2": "헬리팍스(YHZ)",
  "Column3": 1,
  "Column4": 0,
  "Column5": 0
 },
 {
  "조회기간 : 2022.01 ~ 2022.12, 여객 : 전체, 화물 : 전체, 운항 : 전체, 노선 : 전체, 공항 : 인천(ICN), 상대공항 : 전체, 출발\/도착 : 출발": "인천(ICN)",
  "Column2": "호스토멜(GML)",
  "Column3": 2,
  "Column4": 0,
  "Column5": 0
 },
 {
  "조회기간 : 2022.01 ~ 2022.12, 여객 : 전체, 화물 : 전체, 운항 : 전체, 노선 : 전체, 공항 : 인천(ICN), 상대공항 : 전체, 출발\/도착 : 출발": "인천(ICN)",
  "Column2": "멜버른 툴라마린(MEL)",
  "Column3": 0,
  "Column4": 0,
  "Column5": 0
 },
 {
  "조회기간 : 2022.01 ~ 2022.12, 여객 : 전체, 화물 : 전체, 운항 : 전체, 노선 : 전체, 공항 : 인천(ICN), 상대공항 : 전체, 출발\/도착 : 출발": "인천(ICN)",
  "Column2": "오크랜드(미)(OAK)",
  "Column3": 0,
  "Column4": 0,
  "Column5": 0
 },
 {
  "조회기간 : 2022.01 ~ 2022.12, 여객 : 전체, 화물 : 전체, 운항 : 전체, 노선 : 전체, 공항 : 인천(ICN), 상대공항 : 전체, 출발\/도착 : 출발": "인천(ICN)",
  "Column2": "제주(CJU)",
  "Column3": 0,
  "Column4": 0,
  "Column5": 0
 },
 {
  "조회기간 : 2022.01 ~ 2022.12, 여객 : 전체, 화물 : 전체, 운항 : 전체, 노선 : 전체, 공항 : 인천(ICN), 상대공항 : 전체, 출발\/도착 : 출발": "인천(ICN)",
  "Column2": "후잔드 공항(LBD)",
  "Column3": 0,
  "Column4": 0,
  "Column5": 95
 },
 {
  "조회기간 : 2022.01 ~ 2022.12, 여객 : 전체, 화물 : 전체, 운항 : 전체, 노선 : 전체, 공항 : 인천(ICN), 상대공항 : 전체, 출발\/도착 : 출발": "인천(ICN)",
  "Column2": "헌츠빌(HSV)",
  "Column3": 0,
  "Column4": 0,
  "Column5": 0
 },
 {
  "조회기간 : 2022.01 ~ 2022.12, 여객 : 전체, 화물 : 전체, 운항 : 전체, 노선 : 전체, 공항 : 인천(ICN), 상대공항 : 전체, 출발\/도착 : 출발": "인천(ICN)",
  "Column2": "아바칸(ABA)",
  "Column3": 0,
  "Column4": 0,
  "Column5": 0
 },
 {
  "조회기간 : 2022.01 ~ 2022.12, 여객 : 전체, 화물 : 전체, 운항 : 전체, 노선 : 전체, 공항 : 인천(ICN), 상대공항 : 전체, 출발\/도착 : 출발": "인천(ICN)",
  "Column2": "우타파오(UTP)",
  "Column3": 0,
  "Column4": 0,
  "Column5": 0
 },
 {
  "조회기간 : 2022.01 ~ 2022.12, 여객 : 전체, 화물 : 전체, 운항 : 전체, 노선 : 전체, 공항 : 인천(ICN), 상대공항 : 전체, 출발\/도착 : 출발": "인천(ICN)",
  "Column2": "도모데도보(DME)",
  "Column3": 0,
  "Column4": 0,
  "Column5": 375
 },
 {
  "조회기간 : 2022.01 ~ 2022.12, 여객 : 전체, 화물 : 전체, 운항 : 전체, 노선 : 전체, 공항 : 인천(ICN), 상대공항 : 전체, 출발\/도착 : 출발": "인천(ICN)",
  "Column2": "니쯔네바토브스크(NJC)",
  "Column3": 0,
  "Column4": 0,
  "Column5": 0
 },
 {
  "조회기간 : 2022.01 ~ 2022.12, 여객 : 전체, 화물 : 전체, 운항 : 전체, 노선 : 전체, 공항 : 인천(ICN), 상대공항 : 전체, 출발\/도착 : 출발": "인천(ICN)",
  "Column2": "바르나울(BAX)",
  "Column3": 0,
  "Column4": 0,
  "Column5": 0
 },
 {
  "조회기간 : 2022.01 ~ 2022.12, 여객 : 전체, 화물 : 전체, 운항 : 전체, 노선 : 전체, 공항 : 인천(ICN), 상대공항 : 전체, 출발\/도착 : 출발": "인천(ICN)",
  "Column2": "구즈베이(YYR)",
  "Column3": 0,
  "Column4": 0,
  "Column5": 0
 },
 {
  "조회기간 : 2022.01 ~ 2022.12, 여객 : 전체, 화물 : 전체, 운항 : 전체, 노선 : 전체, 공항 : 인천(ICN), 상대공항 : 전체, 출발\/도착 : 출발": "인천(ICN)",
  "Column2": "페어뱅크스(FAI)",
  "Column3": 0,
  "Column4": 0,
  "Column5": 0
 },
 {
  "조회기간 : 2022.01 ~ 2022.12, 여객 : 전체, 화물 : 전체, 운항 : 전체, 노선 : 전체, 공항 : 인천(ICN), 상대공항 : 전체, 출발\/도착 : 출발": "인천(ICN)",
  "Column2": "스텐스테드(STN)",
  "Column3": 0,
  "Column4": 0,
  "Column5": 5165
 },
 {
  "조회기간 : 2022.01 ~ 2022.12, 여객 : 전체, 화물 : 전체, 운항 : 전체, 노선 : 전체, 공항 : 인천(ICN), 상대공항 : 전체, 출발\/도착 : 출발": "인천(ICN)",
  "Column2": "카이로(CAI)",
  "Column3": 0,
  "Column4": 0,
  "Column5": 0
 },
 {
  "조회기간 : 2022.01 ~ 2022.12, 여객 : 전체, 화물 : 전체, 운항 : 전체, 노선 : 전체, 공항 : 인천(ICN), 상대공항 : 전체, 출발\/도착 : 출발": "인천(ICN)",
  "Column2": "사르고사(ZAZ)",
  "Column3": 0,
  "Column4": 0,
  "Column5": 0
 },
 {
  "조회기간 : 2022.01 ~ 2022.12, 여객 : 전체, 화물 : 전체, 운항 : 전체, 노선 : 전체, 공항 : 인천(ICN), 상대공항 : 전체, 출발\/도착 : 출발": "인천(ICN)",
  "Column2": "불가스(BOJ)",
  "Column3": 0,
  "Column4": 0,
  "Column5": 0
 },
 {
  "조회기간 : 2022.01 ~ 2022.12, 여객 : 전체, 화물 : 전체, 운항 : 전체, 노선 : 전체, 공항 : 인천(ICN), 상대공항 : 전체, 출발\/도착 : 출발": "인천(ICN)",
  "Column2": "나이로비(NBO)",
  "Column3": 0,
  "Column4": 0,
  "Column5": 0
 },
 {
  "조회기간 : 2022.01 ~ 2022.12, 여객 : 전체, 화물 : 전체, 운항 : 전체, 노선 : 전체, 공항 : 인천(ICN), 상대공항 : 전체, 출발\/도착 : 출발": "인천(ICN)",
  "Column2": "투르크 메나 바트(CRZ)",
  "Column3": 0,
  "Column4": 0,
  "Column5": 0
 },
 {
  "조회기간 : 2022.01 ~ 2022.12, 여객 : 전체, 화물 : 전체, 운항 : 전체, 노선 : 전체, 공항 : 인천(ICN), 상대공항 : 전체, 출발\/도착 : 출발": "인천(ICN)",
  "Column2": "울란우태(UUD)",
  "Column3": 0,
  "Column4": 0,
  "Column5": 0
 },
 {
  "조회기간 : 2022.01 ~ 2022.12, 여객 : 전체, 화물 : 전체, 운항 : 전체, 노선 : 전체, 공항 : 인천(ICN), 상대공항 : 전체, 출발\/도착 : 출발": "인천(ICN)",
  "Column2": "창사(CSX)",
  "Column3": 0,
  "Column4": 0,
  "Column5": 0
 },
 {
  "조회기간 : 2022.01 ~ 2022.12, 여객 : 전체, 화물 : 전체, 운항 : 전체, 노선 : 전체, 공항 : 인천(ICN), 상대공항 : 전체, 출발\/도착 : 출발": "인천(ICN)",
  "Column2": "뭄바이(BOM)",
  "Column3": 0,
  "Column4": 0,
  "Column5": 0
 }
]